{
  "title": "COMPRE POR MARCA",
  "sections": [
    {
      "type": "custom-html",
      "html": "<p><a href=\"https://www.barradoce.com.br/marcas/deglon\"><img alt=\"\" height=\"77\" src=\"https://ecoms1.com/3967/@v3/1643976452020-deglon.jpg\" width=\"180\" /></a>&nbsp;&nbsp;<a href=\"https://www.barradoce.com.br/marcas/deglon\"><img alt=\"\" height=\"77\" src=\"https://ecoms1.com/3967/@v3/1643976452020-deglon.jpg\" width=\"180\" /></a>&nbsp;&nbsp;<a href=\"https://www.barradoce.com.br/marcas/deglon\"><img alt=\"\" height=\"77\" src=\"https://ecoms1.com/3967/@v3/1643976452020-deglon.jpg\" width=\"180\" /></a>&nbsp;&nbsp;<a href=\"https://www.barradoce.com.br/marcas/deglon\"><img alt=\"\" height=\"77\" src=\"https://ecoms1.com/3967/@v3/1643976452020-deglon.jpg\" width=\"180\" /></a></p>\n\n<p><a href=\"https://www.barradoce.com.br/marcas/deglon\"><img alt=\"\" height=\"77\" src=\"https://ecoms1.com/3967/@v3/1643976452020-deglon.jpg\" width=\"180\" /></a>&nbsp;&nbsp;<a href=\"https://www.barradoce.com.br/marcas/deglon\"><img alt=\"\" height=\"77\" src=\"https://ecoms1.com/3967/@v3/1643976452020-deglon.jpg\" width=\"180\" /></a>&nbsp;&nbsp;<a href=\"https://www.barradoce.com.br/marcas/deglon\"><img alt=\"\" height=\"77\" src=\"https://ecoms1.com/3967/@v3/1643976452020-deglon.jpg\" width=\"180\" /></a>&nbsp;&nbsp;<a href=\"https://www.barradoce.com.br/marcas/deglon\"><img alt=\"\" height=\"77\" src=\"https://ecoms1.com/3967/@v3/1643976452020-deglon.jpg\" width=\"180\" /></a></p>\n\n<p><a href=\"https://www.barradoce.com.br/marcas/deglon\"><img alt=\"\" height=\"77\" src=\"https://ecoms1.com/3967/@v3/1643976452020-deglon.jpg\" width=\"180\" /></a>&nbsp;&nbsp;<a href=\"https://www.barradoce.com.br/marcas/deglon\"><img alt=\"\" height=\"77\" src=\"https://ecoms1.com/3967/@v3/1643976452020-deglon.jpg\" width=\"180\" /></a>&nbsp;&nbsp;<a href=\"https://www.barradoce.com.br/marcas/deglon\"><img alt=\"\" height=\"77\" src=\"https://ecoms1.com/3967/@v3/1643976452020-deglon.jpg\" width=\"180\" /></a>&nbsp;&nbsp;<a href=\"https://www.barradoce.com.br/marcas/deglon\"><img alt=\"\" height=\"77\" src=\"https://ecoms1.com/3967/@v3/1643976452020-deglon.jpg\" width=\"180\" /></a></p>\n"
    }
  ],
  "body": "C﻿onfira os produtos das suas marcas favoritas",
  "meta_title": "Compre utensílios de confeitaria pesquisando por marcas | BarraDoce",
  "meta_description": "Na BarraDoce é fácil pesquisar os produtos de confeitaria da sua marca favorita. Cada marca tem uma página dedicada com todos os itens, para facilitar a sua vida."
}